README.rst
setup.py
subtickettypes/__init__.py
subtickettypes/web_ui.py
subtickettypes/htdocs/tickettypeselect.js
trac_subtickettypes.egg-info/PKG-INFO
trac_subtickettypes.egg-info/SOURCES.txt
trac_subtickettypes.egg-info/dependency_links.txt
trac_subtickettypes.egg-info/entry_points.txt
trac_subtickettypes.egg-info/requires.txt
trac_subtickettypes.egg-info/top_level.txt