Metadata-Version: 1.1
Name: trac-subtickettypes
Version: 0.2.1
Summary: Provides support for sub ticket types in the Trac interface.
Home-page: https://github.com/goodwillcoding/trac-subtickettypes
Author: Michael R
Author-email: UNKNOWN
License: BSD
Keywords: trac plugin ticket types subtickettypes
Platform: UNKNOWN
Classifier: Framework :: Trac
Classifier: Environment :: Web Environment
Classifier: Framework :: Trac
Classifier: License :: OSI Approved :: BSD License
Classifier: Natural Language :: English
Classifier: Operating System :: OS Independent
Classifier: Programming Language :: Python
